grid2demand/__init__.py
grid2demand/_grid2demand.py
grid2demand/func_lib/__init__.py
grid2demand/func_lib/gen_agent_demand.py
grid2demand/func_lib/gen_zone.py
grid2demand/func_lib/gravity_model.py
grid2demand/func_lib/plot_net.py
grid2demand/func_lib/read_node_poi.py
grid2demand/func_lib/read_zone.py
grid2demand/func_lib/save_results.py
grid2demand/func_lib/trip_rate_production_attraction.py
grid2demand/utils_lib/__init__.py
grid2demand/utils_lib/net_utils.py
grid2demand/utils_lib/pkg_settings.py
grid2demand/utils_lib/utils.py
grid2demand-1.0.6.dist-info/METADATA
grid2demand-1.0.6.dist-info/WHEEL
grid2demand-1.0.6.dist-info/top_level.txt
grid2demand-1.0.6.dist-info/RECORD
