Metadata-Version: 2.4
Name: grid2demand
Version: 1.0.6
Summary: A tool for generating zone-to-zone travel demand based on grid cells or TAZs using gravity model
Author-email: Xiangyong Luo <luoxiangyong01@gmail.com>, Xuesong Simon Zhou <xzhou74@asu.edu>
Maintainer-email: Xiangyong Luo <luoxiangyong01@gmail.com>
Project-URL: Homepage, https://github.com/xyluo25/grid2demand
Project-URL: Documentation, https://github.com/xyluo25/grid2demand
Project-URL: Bug_Tracker, https://github.com/xyluo25/grid2demand/issues
Keywords: demand,gravity model,travel demand,zone-to-zone demand,grid cells,TAZs
Classifier: Programming Language :: Python :: 3
Classifier: Programming Language :: Python :: 3.10
Classifier: Programming Language :: Python :: 3.11
Classifier: Programming Language :: Python :: 3.12
Classifier: Programming Language :: Python :: 3.13
Classifier: Intended Audience :: Developers
Classifier: Operating System :: OS Independent
Classifier: Topic :: Software Development :: Libraries
Requires-Python: >=3.10
Requires-Dist: joblib>=1.4.2
Requires-Dist: pandas>=2.2.3
Requires-Dist: pyproj
Requires-Dist: pyufunc>=0.4.1
Requires-Dist: Shapely>=2.0.6
Requires-Dist: tqdm>=4.66.5
Requires-Dist: matplotlib
